path_overrides.py
path_overrides-0.2.data/scripts/path_overrides
path_overrides-0.2.dist-info/DESCRIPTION.rst
path_overrides-0.2.dist-info/METADATA
path_overrides-0.2.dist-info/metadata.json
path_overrides-0.2.dist-info/RECORD
path_overrides-0.2.dist-info/top_level.txt
path_overrides-0.2.dist-info/WHEEL
