Metadata-Version: 2.0
Name: path-overrides
Version: 0.2
Summary: Show executables overriding others with current PATH config
Home-page: http://bitbucket.org/codedstructure/path_overrides
Author: Ben Bass
Author-email: benbass@codedstructure.net
License: MIT
Platform: any
Classifier: Development Status :: 4 - Beta
Classifier: Environment :: Console
Classifier: License :: OSI Approved :: MIT License
Classifier: Operating System :: POSIX
Classifier: Programming Language :: Python :: 2
Classifier: Programming Language :: Python :: 2.7
Classifier: Programming Language :: Python :: 3
Classifier: Programming Language :: Python :: 3.2
Classifier: Programming Language :: Python :: 3.3
Classifier: Programming Language :: Python :: 3.4
Classifier: Topic :: Utilities
